<?xml version="1.0" encoding="utf-8"?>
<odoo>
    <record id="view_helpdesk_project_ticket_form" model="ir.ui.view">
        <field name="name">view.helpdesk.project.ticket.form</field>
        <field name="model">helpdesk.ticket</field>
        <field name="inherit_id" ref="helpdesk_mgmt.ticket_view_form"/>
        <field name="arch" type="xml">
            <notebook position="inside">
              <page name="project" string="Project">
                <group>
                  <field name="project_id"/>
                  <field name="task_id"/>
                </group>
              </page>
            </notebook>
        </field>
    </record>
</odoo>
